{
    "name":"Workflow -1",
    "start_up_node":"reg-step-0",
    "inputData":[
       {"name":"profileId","datatype":"int"},
       {"name":"profile","datatype":"string"}
    ],
    "reg-step-0":{
        "urntype":"service",
        "appCode":"davvag-sample-app-1",
        "componentCode":"app-handler",
        "method":{
            "type":"post",
            "name":"Save",
            "params":[{"name":"postData","type":"object","value":"inputData"}],
            "return":true,
            "returnobj":"fbresp"
        },
        "success":"reg-step-1",
        "fail":"nodefail"
    },"reg-step-1":{
        "urntype":"service",
        "appCode":"stelup_shop",
        "componentCode":"seller_svr",
        "method":{
            "type":"get",
            "name":"Orders",
            "params":[{"name":"type","value":"accepted"}],
            "return":true,
            "returnobj":"fbresp2"
        },
        "success":"reg-step-2",
        "fail":"nodefail"
    },"reg-step-2":{
        "urntype":"create_object",
        "name":"stelup_shop",
        "method":{
            "type":"create_object",
            "name":"Orders",
            "return":true,
            "returnobj":"lessjob"
        },
        "variables":[
            {"name":"postData","type":"object","value":"inputData"},
            {"name":"profileId","type":"object","value":"inputData.profileId"},
            {"name":"profile","type":"object","value":"inputData.profile"},
            {"name":"da_mo","value":"hello world!"}
        ]
           ,
        "fail":"nodefail"
    },"nodefail":{
        "urntype":"class",
        "file":"test.php",
        "class":"test",
        "method":{
            "name":"fail",
            "params":[{"inputData":"name"}],
            "return":true,
            "returnobj":"failed"
        }
    }
}